{
  "main": {
    "id": "042951836fdc6524",
    "type": "split",
    "children": [
      {
        "id": "e0a1d3b0970de39a",
        "type": "tabs",
        "children": [
          {
            "id": "ec16f18d7c2b9eaa",
            "type": "leaf",
            "state": {
              "type": "markdown",
              "state": {
                "file": "AppSec/TryHackMe/Injections/XEE/Exploits/In-Band XXE.md",
                "mode": "source",
                "source": false
              },
              "icon": "lucide-file",
              "title": "In-Band XXE"
            }
          },
          {
            "id": "66ff3554aa1fbaa8",
            "type": "leaf",
            "state": {
              "type": "release-notes",
              "state": {
                "currentVersion": "1.8.3"
              },
              "icon": "lucide-book-up",
              "title": "Release Notes 1.8.3"
            }
          }
        ],
        "currentTab": 1
      }
    ],
    "direction": "vertical"
  },
  "left": {
    "id": "e6443c469d3a1c22",
    "type": "split",
    "children": [
      {
        "id": "2f2762485ebafd25",
        "type": "tabs",
        "children": [
          {
            "id": "de55c564cd05073b",
            "type": "leaf",
            "state": {
              "type": "file-explorer",
              "state": {
                "sortOrder": "alphabetical",
                "autoReveal": false
              },
              "icon": "lucide-folder-closed",
              "title": "Files"
            }
          },
          {
            "id": "b42d4358b5932d96",
            "type": "leaf",
            "state": {
              "type": "search",
              "state": {
                "query": "",
                "matchingCase": false,
                "explainSearch": false,
                "collapseAll": false,
                "extraContext": false,
                "sortOrder": "alphabetical"
              },
              "icon": "lucide-search",
              "title": "Search"
            }
          },
          {
            "id": "eb78f6ada6eaff06",
            "type": "leaf",
            "state": {
              "type": "bookmarks",
              "state": {},
              "icon": "lucide-bookmark",
              "title": "Bookmarks"
            }
          }
        ]
      }
    ],
    "direction": "horizontal",
    "width": 247.5
  },
  "right": {
    "id": "a7ca32e1cb9c75d4",
    "type": "split",
    "children": [
      {
        "id": "37a97ce184cea19f",
        "type": "tabs",
        "children": [
          {
            "id": "90a84dc5576f5723",
            "type": "leaf",
            "state": {
              "type": "backlink",
              "state": {
                "file": "TryHackMe/PenTest/Jr.Penetration Tester/WEB Attacks/SQL Injections.md",
                "collapseAll": false,
                "extraContext": false,
                "sortOrder": "alphabetical",
                "showSearch": false,
                "searchQuery": "",
                "backlinkCollapsed": false,
                "unlinkedCollapsed": true
              },
              "icon": "links-coming-in",
              "title": "Backlinks for SQL Injections"
            }
          },
          {
            "id": "37ad2237f28f1066",
            "type": "leaf",
            "state": {
              "type": "outgoing-link",
              "state": {
                "file": "TryHackMe/PenTest/Jr.Penetration Tester/WEB Attacks/SQL Injections.md",
                "linksCollapsed": false,
                "unlinkedCollapsed": true
              },
              "icon": "links-going-out",
              "title": "Outgoing links from SQL Injections"
            }
          },
          {
            "id": "6ed8f1d36ab4a9cd",
            "type": "leaf",
            "state": {
              "type": "tag",
              "state": {
                "sortOrder": "frequency",
                "useHierarchy": true
              },
              "icon": "lucide-tags",
              "title": "Tags"
            }
          },
          {
            "id": "5bf849d60880a38f",
            "type": "leaf",
            "state": {
              "type": "outline",
              "state": {
                "file": "AppSec/TryHackMe/Injections/XEE/Exploits/In-Band XXE.md",
                "followCursor": false,
                "showSearch": false,
                "searchQuery": ""
              },
              "icon": "lucide-list",
              "title": "Outline of In-Band XXE"
            }
          }
        ],
        "currentTab": 3
      }
    ],
    "direction": "horizontal",
    "width": 200
  },
  "left-ribbon": {
    "hiddenItems": {
      "switcher:Open quick switcher": false,
      "graph:Open graph view": false,
      "canvas:Create new canvas": false,
      "daily-notes:Open today's daily note": false,
      "templates:Insert template": false,
      "command-palette:Open command palette": false
    }
  },
  "active": "66ff3554aa1fbaa8",
  "lastOpenFiles": [
    "AppSec/TryHackMe/Injections/XEE/Exploits/Out-of-Band XXE.md",
    "AppSec/TryHackMe/Injections/XEE/Exploits/SSRF + XXE.md",
    "AppSec/TryHackMe/Injections/ORM/Exploits/Weak Implementation.md",
    "AppSec/TryHackMe/Injections/ORM/Exploits/Vulnerable Implementation.md",
    "AppSec/TryHackMe/Injections/ORM/Exploits/Techniques for Testing ORM Injection.md",
    "AppSec/TryHackMe/Server-Side Attacks/Challenge - Include.md",
    "z.Screenshots/Pasted image 20250129224431.png",
    "z.Screenshots/Pasted image 20250129224422.png",
    "z.Screenshots/Pasted image 20250129224413.png",
    "z.Screenshots/Pasted image 20250129224331.png",
    "AppSec/TryHackMe/Injections/Challenge - Injectics.md",
    "z.Screenshots/Pasted image 20250129222533.png",
    "z.Screenshots/Pasted image 20250129222303.png",
    "PenTest/TryHackMe/Network Security/Enumeration/Content Discovery.md",
    "z.Screenshots/Pasted image 20250129222023.png",
    "z.Screenshots/Pasted image 20250129221819.png",
    "z.Screenshots/Pasted image 20250129221740.png",
    "z.Screenshots/Pasted image 20250129222112.png",
    "AppSec/TryHackMe/Server-Side Attacks/SSRF/Exploits/Server Crash.md",
    "AppSec/TryHackMe/Server-Side Attacks/SSRF/Exploits/Blind.md",
    "AppSec/TryHackMe/Server-Side Attacks/SSRF/Exploits/Basic.md",
    "AppSec/TryHackMe/Server-Side Attacks/Prototype Pollution/Exploits/XSS.md",
    "AppSec/TryHackMe/Server-Side Attacks/Prototype Pollution/Exploits/Denial of Service.md",
    "AppSec/TryHackMe/Server-Side Attacks/Prototype Pollution/Exploits/Property Injection.md",
    "AppSec/TryHackMe/Server-Side Attacks/Prototype Pollution/0)Summary.md",
    "PenTest/TryHackMe/Network Security/Enumeration/Subdomain Enumeration.md",
    "AppSec/TryHackMe/Server-Side Attacks/Prototype Pollution/Best Practices.md",
    "AppSec/TryHackMe/Server-Side Attacks/Prototype Pollution/Automation/Scripts.md",
    "AppSec/PortSwigger/CSRF - Cross Site Request Forgery.md",
    "Frameworks & Tools.md",
    "AppSec/TryHackMe/Client-Side Attacks/CSRF/Exploits/Double Submit Cookie Bypass.md",
    "AppSec/TryHackMe/Client-Side Attacks/CSRF/Exploits/Samesite Cookie Bypass.md",
    "AppSec/TryHackMe/Client-Side Attacks/CSRF/Exploits/Basic CSRF - Hidden Link & Image Exploitation.md",
    "AppSec/TryHackMe/Client-Side Attacks/CSRF/Mitigations.md",
    "AppSec/TryHackMe/Client-Side Attacks/CSRF/0)Summary.md",
    "AppSec/TryHackMe/Injections/ORM/0)Summary.md",
    "AppSec/TryHackMe/Server-Side Attacks/Prototype Pollution/Automation",
    "AppSec/TryHackMe/Server-Side Attacks/Prototype Pollution/Exploits",
    "AppSec/TryHackMe/Server-Side Attacks/Prototype Pollution",
    "AppSec/TryHackMe/Server-Side Attacks/Race Conditions/Exploits",
    "AppSec/TryHackMe/Server-Side Attacks/Race Conditions",
    "CTFs/Hackout/AWS/Enumeration/Permissions",
    "CTFs/Hackout/AWS/Lateral Movement",
    "CTFs/Hackout/AWS/Enumeration/Machines",
    "CTFs/Hackout/AWS/Enumeration",
    "CTFs/Hackout/AWS"
  ]
}